slotomania/__init__.py
slotomania/core.py
slotomania/debugger.py
slotomania/exceptions.py
slotomania/contrib/__init__.py
slotomania/contrib/contracts.py
slotomania/contrib/jwt_auth.py
slotomania/contrib/tests/__init__.py
slotomania-0.1.6.data/scripts/fix_sloto_stubs.py
slotomania-0.1.6.dist-info/METADATA
slotomania-0.1.6.dist-info/RECORD
slotomania-0.1.6.dist-info/WHEEL
slotomania-0.1.6.dist-info/top_level.txt
