Metadata-Version: 2.1
Name: slotomania
Version: 0.1.6
Summary: Slotomania
Home-page: https://github.com/conanfanli/slotomania
Author: Conan Li
Author-email: conanlics@gmail.com
License: MIT
Keywords: slotomania
Platform: UNKNOWN
Classifier: Development Status :: 3 - Alpha
Classifier: License :: OSI Approved :: MIT License
Classifier: Programming Language :: Python :: 3.6
Classifier: Programming Language :: Python :: 3.7
Requires-Python: ~=3.6
Provides-Extra: dev
Requires-Dist: yapf (>=0.21)
Provides-Extra: dev
Requires-Dist: ipython; extra == 'dev'
Requires-Dist: mypy; extra == 'dev'
